sql_compiler/__init__.py
sql_compiler/manager.py
sql_compiler/queryset.py
sql_compiler/utils.py
sql_compiler/compilers/__init__.py
sql_compiler/compilers/base.py
sql_compiler/compilers/mysql.py
sql_compiler/compilers/postgresql.py
django_sql_compiler-0.1.0.dist-info/METADATA
django_sql_compiler-0.1.0.dist-info/WHEEL
django_sql_compiler-0.1.0.dist-info/top_level.txt
django_sql_compiler-0.1.0.dist-info/RECORD
