Metadata-Version: 2.1
Name: django-sql-compiler
Version: 0.1.0
Summary: A light-weight module to generate usable SQL from a Django QuerySet.
Home-page: https://github.com/GrokData/django-sql-compiler
Author: Grok Data / Jared Stufft
Author-email: jared@grokdata.tech
License: MIT
Platform: UNKNOWN
Classifier: Development Status :: 3 - Alpha
Classifier: Environment :: Web Environment
Classifier: Framework :: Django
Classifier: License :: OSI Approved :: MIT License
Classifier: Programming Language :: Python :: 3
Classifier: Topic :: Internet :: WWW/HTTP
Classifier: Topic :: Software Development :: Libraries :: Python Modules
Requires-Dist: django
